brainglobe_sphinx_config/__init__.py
brainglobe_sphinx_config/_templates/header.html
brainglobe_sphinx_config/_templates/header_links.json
brainglobe_sphinx_config/_templates/version.html
brainglobe_sphinx_config-0.1b1.dist-info/LICENSE
brainglobe_sphinx_config-0.1b1.dist-info/METADATA
brainglobe_sphinx_config-0.1b1.dist-info/WHEEL
brainglobe_sphinx_config-0.1b1.dist-info/top_level.txt
brainglobe_sphinx_config-0.1b1.dist-info/RECORD
